solo_cli.py
solo_cli-1.1.4.dist-info/METADATA
solo_cli-1.1.4.dist-info/WHEEL
solo_cli-1.1.4.dist-info/entry_points.txt
solo_cli-1.1.4.dist-info/top_level.txt
solo_cli-1.1.4.dist-info/RECORD
