Metadata-Version: 2.1
Name: solo-cli
Version: 1.1.4
Summary: A CLI to install and manage Ollama, and serve OpenUI with ngrok
Home-page: https://github.com/yourusername/solo-cli
Author: Dhruv Diddi
Author-email: your.email@example.com
Classifier: Programming Language :: Python :: 3
Classifier: License :: OSI Approved :: MIT License
Classifier: Operating System :: OS Independent
Requires-Python: >=3.6
Requires-Dist: click
